torchmed/__init__.py
torchmed/datasets/__init__.py
torchmed/datasets/medcombiner.py
torchmed/datasets/medfile.py
torchmed/datasets/medfolder.py
torchmed/patterns/__init__.py
torchmed/patterns/patch.py
torchmed/readers/__init__.py
torchmed/readers/cv.py
torchmed/readers/nib.py
torchmed/readers/pil.py
torchmed/readers/reader.py
torchmed/readers/simpleitk.py
torchmed/samplers/__init__.py
torchmed/samplers/mask_sampler.py
torchmed/samplers/sampler.py
torchmed/utils/__init__.py
torchmed/utils/augmentation.py
torchmed/utils/file.py
torchmed/utils/logger_plotter.py
torchmed/utils/loss.py
torchmed/utils/metric.py
torchmed/utils/multiproc.py
torchmed/utils/preprocessing.py
torchmed/utils/transforms.py
torchmed-0.0.1a0.dist-info/METADATA
torchmed-0.0.1a0.dist-info/WHEEL
torchmed-0.0.1a0.dist-info/top_level.txt
torchmed-0.0.1a0.dist-info/RECORD
