Metadata-Version: 2.1
Name: torchmed
Version: 0.0.1a0
Summary: A compagnon library for deep learning on medical imaging
Home-page: https://github.com/trypag/pytorch-med
Author: Pierre-Antoine Ganaye
License: GNU GPLv3
Platform: UNKNOWN
Classifier: Programming Language :: Python :: 3
Classifier: License :: OSI Approved :: GNU General Public License v3 (GPLv3)
Classifier: Operating System :: POSIX
Requires-Python: >=3
Requires-Dist: torch (>=1.0.0)
Requires-Dist: nibabel
Requires-Dist: SimpleITK
Requires-Dist: Pillow
Requires-Dist: numpy
Requires-Dist: pandas
Requires-Dist: scipy
Requires-Dist: matplotlib
Requires-Dist: opencv-python
